<?xml version="1.0" encoding="utf-8"?>
<languageData>
	<fileversion major="1" minor="5" />
	<systemkeyboard path="en_US" />
	<textprint fontid="0" size="10" bold="0" italic="0" />
	<fonts>
		<font id="0" fontname="Arial" filename="arial.ttf" fontsizefactor="100" regular="1" bold="0" italic="0" />
		<font id="1" fontname="Arial Bold" filename="arialbd.ttf" fontsizefactor="100" regular="0" bold="1" italic="0" />
		<font id="2" fontname="Arial Italic" filename="ariali.ttf" fontsizefactor="100" regular="0" bold="0" italic="1" />
	</fonts>
	<texts>
		<standard>
			<s ID="0"><![CDATA[Penerima Tekanan Balik ]]></s>
			<s ID="1"><![CDATA[Rev 10.1]]></s>
			<s ID="2"><![CDATA[Manual Mode]]></s>
			<s ID="3"><![CDATA[Auto Mode]]></s>
			<s ID="4"><![CDATA[CO]]></s>
			<s ID="5"><![CDATA[PB]]></s>
			<s ID="6"><![CDATA[TI]]></s>
			<s ID="7"><![CDATA[TD]]></s>
			<s ID="8"><![CDATA[HiHi]]></s>
			<s ID="9"><![CDATA[Hi]]></s>
			<s ID="10"><![CDATA[Lo]]></s>
			<s ID="11"><![CDATA[Exhaust Valve Buka]]></s>
			<s ID="12"><![CDATA[Exhaust Valve Tutup]]></s>
			<s ID="13"><![CDATA[High Alarm]]></s>
			<s ID="14"><![CDATA[EXHAUST SETTING]]></s>
			<s ID="15"><![CDATA[EXHAUST PID SETTING]]></s>
			<s ID="16"><![CDATA[EXHAUST OPEN TIME]]></s>
			<s ID="18"><![CDATA[MAKEUP PID SETTING]]></s>
			<s ID="19"><![CDATA[Steam Masuk: Tidak Cukup]]></s>
			<s ID="20"><![CDATA[Steam Masuk: Cukup]]></s>
			<s ID="22"><![CDATA[MAKEUP SETPOINT]]></s>
			<s ID="24"><![CDATA[BPR Pressure Transmitter Rusak]]></s>
			<s ID="25"><![CDATA[VESSEL PRESSURE]]></s>
			<s ID="28"><![CDATA[Min        Max]]></s>
			<s ID="31"><![CDATA[BPR Setting]]></s>
			<s ID="32"><![CDATA[Supply Pressure Transmitter Rusak]]></s>
			<s ID="33"><![CDATA[BOILER]]></s>
			<s ID="34"><![CDATA[BPR]]></s>
			<s ID="35"><![CDATA[Makeup Valve]]></s>
			<s ID="37"><![CDATA[Exhaust Valve]]></s>
			<s ID="38"><![CDATA[EU High Limit]]></s>
			<s ID="39"><![CDATA[EU Low Limit]]></s>
			<s ID="40"><![CDATA[SUPPLY PRESSURE]]></s>
			<s ID="41"><![CDATA[PV High Limit < 580 Psi]]></s>
			<s ID="42"><![CDATA[PV Low Limit < 290 Psi]]></s>
			<s ID="43"><![CDATA[EXHAUST OFF TIME]]></s>
			<s ID="45"><![CDATA[Exhaust Valve Modulating]]></s>
			<s ID="46"><![CDATA[Exhaust Valve On/Off ]]></s>
			<s ID="48"><![CDATA[SP]]></s>
			<s ID="49"><![CDATA[No User]]></s>
			<s ID="50"><![CDATA[Psi]]></s>
			<s ID="51"><![CDATA[BAR]]></s>
			<s ID="53"><![CDATA[%]]></s>
			<s ID="54"><![CDATA[Detik]]></s>
			<s ID="55"><![CDATA[Informasi Hardware & Software]]></s>
			<s ID="56"><![CDATA[User Management]]></s>
			<s ID="57"><![CDATA[Project Name :]]></s>
			<s ID="58"><![CDATA[Serial No :]]></s>
			<s ID="59"><![CDATA[Runtime Version :]]></s>
			<s ID="60"><![CDATA[Touch Version :]]></s>
			<s ID="61"><![CDATA[Compiler Version :]]></s>
			<s ID="62"><![CDATA[Hardware Version :]]></s>
			<s ID="63"><![CDATA[OS Version :]]></s>
			<s ID="64"><![CDATA[Admin]]></s>
			<s ID="65"><![CDATA[Power]]></s>
			<s ID="66"><![CDATA[Support]]></s>
			<s ID="67"><![CDATA[User]]></s>
			<s ID="68"><![CDATA[Set Hari]]></s>
			<s ID="69"><![CDATA[Set Bulan]]></s>
			<s ID="70"><![CDATA[Set Tahun]]></s>
			<s ID="71"><![CDATA[Set Jam]]></s>
			<s ID="72"><![CDATA[Set Menit]]></s>
			<s ID="73"><![CDATA[Set Tanggal & Jam]]></s>
			<s ID="74"><![CDATA[Hapus User]]></s>
			<s ID="75"><![CDATA[Buat User Baru]]></s>
			<s ID="76"><![CDATA[Log In]]></s>
			<s ID="77"><![CDATA[Log Out]]></s>
			<s ID="78"><![CDATA[Ganti Password]]></s>
			<s ID="79"><![CDATA[Lain User]]></s>
			<s ID="80"><![CDATA[Pribadi]]></s>
			<s ID="81"><![CDATA[Psi < -- > BAR]]></s>
			<s ID="82"><![CDATA[BPR Setting]]></s>
			<s ID="84"><![CDATA[System Setting]]></s>
			<s ID="88"><![CDATA[PT Type: 0 = 0-5 Bar, 1 = 0-4 Bar & 2 = 0-6 Bar]]></s>
			<s ID="89"><![CDATA[Flushing through STR: 0 = Disable, 1 = Enable ]]></s>
			<s ID="90"><![CDATA[Exhaust Valve: 0 = On/Off , 1 = Madulating]]></s>
			<s ID="91"><![CDATA[System Parameter]]></s>
			<s ID="92"><![CDATA[Waktu @ Garis]]></s>
			<s ID="93"><![CDATA[Lihat Simpanan]]></s>
			<s ID="94"><![CDATA[Hapus Buffer]]></s>
			<s ID="95"><![CDATA[Print Screen]]></s>
			<s ID="97"><![CDATA[Graph History]]></s>
			<s ID="101"><![CDATA[Graph Live]]></s>
			<s ID="103"><![CDATA[Graph Recording: 0 = Disable, 1 = Enable]]></s>
			<s ID="104"><![CDATA[Graph Refresh: 1 = 8 hourly, 2 = 12 hourly, 3 = 24 hourly]]></s>
			<s ID="105"><![CDATA[Graph Start to Record: xx (hh:00)]]></s>
			<s ID="106"><![CDATA[Logic Name :]]></s>
			<s ID="107"><![CDATA[SHUTDOWN]]></s>
			<s ID="108"><![CDATA[]]></s>
			<s ID="109"><![CDATA[]]></s>
			<s ID="110"><![CDATA[]]></s>
			<s ID="111"><![CDATA[]]></s>
		</standard>
		<help />
		<error />
		<system>
			<sys ID="0"><![CDATA[%1]]></sys>
			<sys ID="1"><![CDATA[%1]]></sys>
			<sys ID="2"><![CDATA[Can't find or read from file '%1']]></sys>
			<sys ID="3"><![CDATA[Can't read from text number <%1!d!> from file '%2' !]]></sys>
			<sys ID="4"><![CDATA[Project entry screen (%1) not found !]]></sys>
			<sys ID="5"><![CDATA[No matching file found (%1) !]]></sys>
			<sys ID="6"><![CDATA[No more memory available for function %1 !]]></sys>
			<sys ID="7"><![CDATA[Some texts in textfile '%1' are missing !]]></sys>
			<sys ID="8"><![CDATA[Accessing '%1' failed with error '%2' !]]></sys>
			<sys ID="9"><![CDATA[The function < %1 > is not supported !]]></sys>
			<sys ID="10"><![CDATA[Touch is dirty or defect!]]></sys>
			<sys ID="11"><![CDATA[Can't create or write to file '%1' !]]></sys>
			<sys ID="12"><![CDATA[Header information in file is invalid (%1) !]]></sys>
			<sys ID="13"><![CDATA[Recipe with id < %1 > not found]]></sys>
			<sys ID="14"><![CDATA[Can't save recipe with empty name !]]></sys>
			<sys ID="15"><![CDATA[The recipe name '%1' already exist ! Choose another name.]]></sys>
			<sys ID="16"><![CDATA[Execution of function %1 has failed (%2) !]]></sys>
			<sys ID="17"><![CDATA[Error in script %1 !]]></sys>
			<sys ID="18"><![CDATA[Can't read from file '%1' - structure mismatch!]]></sys>
			<sys ID="19"><![CDATA[No user authorization for %1 !]]></sys>
			<sys ID="20"><![CDATA[Communication disturbed: '%1' !]]></sys>
			<sys ID="21"><![CDATA[Not enough Diskspace available (%1 kB)]]></sys>
			<sys ID="22"><![CDATA[Protected or invalid path defined (%1) !]]></sys>
			<sys ID="23"><![CDATA[Printer not ready !]]></sys>
			<sys ID="24"><![CDATA[Printer busy !]]></sys>
			<sys ID="25"><![CDATA[Incorrect Galileo license key (%1) - DEMO mode !]]></sys>
			<sys ID="26"><![CDATA[No valid runtime license found - DEMO mode !]]></sys>
			<sys ID="27"><![CDATA[Demo mode has expired! Runtime will shut down.]]></sys>
			<sys ID="28"><![CDATA[Printer < %1 > not detected !]]></sys>
			<sys ID="29"><![CDATA[%1 (%2)]]></sys>
			<sys ID="30"><![CDATA[Authentication failed: Username and/or password wrong]]></sys>
			<sys ID="31"><![CDATA[Username is empty]]></sys>
			<sys ID="32"><![CDATA[Password is empty]]></sys>
			<sys ID="33"><![CDATA[No group selected]]></sys>
			<sys ID="34"><![CDATA[Your password has expired and must be changed]]></sys>
			<sys ID="35"><![CDATA[Too many failed login attempts, the account is locked]]></sys>
			<sys ID="36"><![CDATA[Cannot create user: Number of users has reached the maximum]]></sys>
			<sys ID="37"><![CDATA[Group '%1' does not exist]]></sys>
			<sys ID="38"><![CDATA[User '%1' does not exist]]></sys>
			<sys ID="39"><![CDATA[User '%1' already exists]]></sys>
			<sys ID="40"><![CDATA[New Password must differ from current one]]></sys>
			<sys ID="41"><![CDATA[New Password already used in history]]></sys>
			<sys ID="42"><![CDATA[Cannot confirm new password: not matching]]></sys>
			<sys ID="43"><![CDATA[No active user present. Please login to perform action]]></sys>
			<sys ID="44"><![CDATA[User '%1' is locked]]></sys>
			<sys ID="45"><![CDATA[Password is too short. Type at least %1 characters]]></sys>
			<sys ID="46"><![CDATA[Cannot lock active user]]></sys>
			<sys ID="47"><![CDATA[Cannot delete active user]]></sys>
			<sys ID="48"><![CDATA[No permission to create user in group '%1']]></sys>
			<sys ID="49"><![CDATA[No permission to delete user '%1' in group '%2']]></sys>
			<sys ID="50"><![CDATA[No permission to change password of user '%1']]></sys>
			<sys ID="51"><![CDATA[No permission to change group of user '%1']]></sys>
			<sys ID="52"><![CDATA[No permission to modify group '%1']]></sys>
			<sys ID="53"><![CDATA[No permission to lock user '%1']]></sys>
			<sys ID="54"><![CDATA[No permission to unlock user '%1']]></sys>
			<sys ID="55"><![CDATA[No permission to create users on this device]]></sys>
			<sys ID="56"><![CDATA[No permission to delete users on this device]]></sys>
			<sys ID="57"><![CDATA[No permission to change passwords]]></sys>
			<sys ID="58"><![CDATA[No permission to change group affiliations]]></sys>
			<sys ID="59"><![CDATA[No permission to lock/unlock users]]></sys>
			<sys ID="60"><![CDATA[Successfully created user '%1']]></sys>
			<sys ID="61"><![CDATA[Successfully deleted user '%1']]></sys>
			<sys ID="62"><![CDATA[Successfully locked user '%1']]></sys>
			<sys ID="63"><![CDATA[Successfully unlocked user '%1']]></sys>
			<sys ID="64"><![CDATA[Successfully changed password of user '%1']]></sys>
			<sys ID="65"><![CDATA[Successfully changed group of user '%1']]></sys>
			<sys ID="66"><![CDATA[GraphBlock is running. Please stop to perform file loading.]]></sys>
		</system>
	</texts>
</languageData>